odoo/addons/account_invoice_pricelist_technical/README.rst
odoo/addons/account_invoice_pricelist_technical/__init__.py
odoo/addons/account_invoice_pricelist_technical/__manifest__.py
odoo/addons/account_invoice_pricelist_technical/i18n/account_invoice_pricelist_technical.pot
odoo/addons/account_invoice_pricelist_technical/i18n/de.po
odoo/addons/account_invoice_pricelist_technical/i18n/fr.po
odoo/addons/account_invoice_pricelist_technical/models/__init__.py
odoo/addons/account_invoice_pricelist_technical/models/account_move.py
odoo/addons/account_invoice_pricelist_technical/readme/CONTRIBUTORS.rst
odoo/addons/account_invoice_pricelist_technical/readme/DESCRIPTION.rst
odoo/addons/account_invoice_pricelist_technical/static/description/icon.png
odoo/addons/account_invoice_pricelist_technical/static/description/index.html
odoo_addon_account_invoice_pricelist_technical-16.0.1.0.0.3.dist-info/METADATA
odoo_addon_account_invoice_pricelist_technical-16.0.1.0.0.3.dist-info/WHEEL
odoo_addon_account_invoice_pricelist_technical-16.0.1.0.0.3.dist-info/top_level.txt
odoo_addon_account_invoice_pricelist_technical-16.0.1.0.0.3.dist-info/RECORD
