Metadata-Version: 2.1
Name: odoo-addon-account_invoice_pricelist_technical
Version: 16.0.1.0.0.3
Summary: Prevent technical pricelists from being selected on invoice forms
Home-page: https://github.com/OCA/sale-workflow
Author: GRAP,Odoo Community Association (OCA)
Author-email: support@odoo-community.org
License: AGPL-3
Classifier: Programming Language :: Python
Classifier: Framework :: Odoo
Classifier: Framework :: Odoo :: 16.0
Classifier: License :: OSI Approved :: GNU Affero General Public License v3
Requires-Python: >=3.10
Requires-Dist: odoo-addon-account-invoice-pricelist<16.1dev,>=16.0dev
Requires-Dist: odoo-addon-sale-pricelist-technical<16.1dev,>=16.0dev
Requires-Dist: odoo<16.1dev,>=16.0a
